NLP/__init__.py
NLP_python-1.1.0.dist-info/LICENSE
NLP_python-1.1.0.dist-info/METADATA
NLP_python-1.1.0.dist-info/WHEEL
NLP_python-1.1.0.dist-info/top_level.txt
NLP_python-1.1.0.dist-info/RECORD
