Metadata-Version: 2.1
Name: NLP-python
Version: 1.1.0
Summary: Natural Language Processing to detect sentences are positive or negative
Home-page: https://github.com/HurinHu/NLP-python
Author: Hurin Hu
Author-email: hurin@live.ca
License: UNKNOWN
Platform: UNKNOWN
Classifier: Programming Language :: Python :: 3
Classifier: License :: OSI Approved :: MIT License
Classifier: Operating System :: OS Independent
Requires-Dist: scikit-learn
Requires-Dist: pandas
Requires-Dist: numpy
